dictplus/__init__.py
dictplus/dictplus.py
dictplus-0.0.15.dist-info/DESCRIPTION.rst
dictplus-0.0.15.dist-info/METADATA
dictplus-0.0.15.dist-info/RECORD
dictplus-0.0.15.dist-info/WHEEL
dictplus-0.0.15.dist-info/metadata.json
dictplus-0.0.15.dist-info/top_level.txt
dictplus-0.0.15.dist-info/zip-safe
