Metadata-Version: 2.0
Name: dictplus
Version: 0.0.15
Summary: enhanced dictionary
Home-page: https://github.com/PhantomKidding
Author: cchen224
Author-email: phantomkidding@gmail.com
License: MIT License
Keywords: enhanced dictionary
Platform: any
Requires-Dist: pandas
